BJSnum/__init__.py
BJSnum/add.py
BJSnum/div_flr.py
BJSnum/div_norm.py
BJSnum/mod.py
BJSnum/mult.py
BJSnum/pow_.py
BJSnum/sub.py
bjsnum-0.1.6.dist-info/WHEEL
bjsnum-0.1.6.dist-info/METADATA
bjsnum-0.1.6.dist-info/RECORD
