Metadata-Version: 2.4
Name: BJSnum
Version: 0.1.6
Summary: A simple numerical operations library
Author-email: BJS <coderbjs@gmail.com>
Requires-Python: >=3.13.7
Requires-Dist: numpy
